elastictoolkit/__init__.py
elastictoolkit/exceptions.py
elastictoolkit/adapters/__init__.py
elastictoolkit/adapters/baseelasticsearchadapter.py
elastictoolkit/adapters/elasticsearch5adapter.py
elastictoolkit/adapters/elasticsearch8adapter.py
elastictoolkit/adapters/exceptions.py
elastictoolkit/constants/__init__.py
elastictoolkit/constants/client.py
elastictoolkit/indexes/__init__.py
elastictoolkit/indexes/baseindex.py
elastictoolkit/indexes/elasticsearch5index.py
elastictoolkit/indexes/elasticsearch8index.py
elastictoolkit/indexes/exceptions.py
elastictoolkit/queryutils/__init__.py
elastictoolkit/queryutils/consts.py
elastictoolkit/queryutils/types.py
elastictoolkit/queryutils/builder/__init__.py
elastictoolkit/queryutils/builder/base.py
elastictoolkit/queryutils/builder/booldirective.py
elastictoolkit/queryutils/builder/custommatchdirective.py
elastictoolkit/queryutils/builder/customscorefunctiondirective.py
elastictoolkit/queryutils/builder/directiveengine.py
elastictoolkit/queryutils/builder/directivevaluemapper.py
elastictoolkit/queryutils/builder/functionscoreengine.py
elastictoolkit/queryutils/builder/matchdirective.py
elastictoolkit/queryutils/builder/matchdirectivebuilder.py
elastictoolkit/queryutils/builder/scorefunctiondirective.py
elastictoolkit/queryutils/builder/scorefunctiondirectivebuilder.py
elastictoolkit/queryutils/builder/helpers/__init__.py
elastictoolkit/queryutils/builder/helpers/directivehelper.py
elastictoolkit/queryutils/builder/helpers/painlesshelper.py
elastictoolkit/queryutils/builder/helpers/valueparser.py
elastictoolkit/queryutils/builder/helpers/valuetransformer.py
elastictoolkit/queryutils/executor/__init__.py
elastictoolkit/utils/__init__.py
elastictoolkit/utils/singleton.py
elastictoolkit_py-0.5.0.dist-info/licenses/LICENSE
tests/queryutils/__init__.py
tests/queryutils/builder/__init__.py
tests/queryutils/builder/basetestcase.py
tests/queryutils/builder/test_customdirective.py
tests/queryutils/builder/test_directiveengine.py
tests/queryutils/builder/test_functionscoreengine.py
elastictoolkit_py-0.5.0.dist-info/METADATA
elastictoolkit_py-0.5.0.dist-info/WHEEL
elastictoolkit_py-0.5.0.dist-info/top_level.txt
elastictoolkit_py-0.5.0.dist-info/RECORD
